brightway2/__init__.py
brightway2-2.4.5.dist-info/AUTHORS.txt
brightway2-2.4.5.dist-info/LICENSE.txt
brightway2-2.4.5.dist-info/METADATA
brightway2-2.4.5.dist-info/WHEEL
brightway2-2.4.5.dist-info/top_level.txt
brightway2-2.4.5.dist-info/RECORD
