Metadata-Version: 2.1
Name: brightway2
Version: 2.4.5
Home-page: https://github.com/brightway-lca/brightway2
Author: Chris Mutel
Author-email: cmutel@gmail.com
License: Copyright (c) 2016, Chris Mutel and ETH Zurich.
Classifier: Development Status :: 5 - Production/Stable
Classifier: Intended Audience :: End Users/Desktop
Classifier: Intended Audience :: Developers
Classifier: Intended Audience :: Science/Research
Classifier: License :: OSI Approved :: BSD License
Classifier: Operating System :: MacOS :: MacOS X
Classifier: Operating System :: Microsoft :: Windows
Classifier: Operating System :: POSIX
Classifier: Programming Language :: Python
Classifier: Programming Language :: Python :: 2.7
Classifier: Programming Language :: Python :: 2 :: Only
Classifier: Topic :: Scientific/Engineering :: Information Analysis
Classifier: Topic :: Scientific/Engineering :: Mathematics
Classifier: Topic :: Scientific/Engineering :: Visualization
License-File: LICENSE.txt
License-File: AUTHORS.txt
Requires-Dist: appdirs
Requires-Dist: asteval
Requires-Dist: bw2analyzer <0.10.99
Requires-Dist: bw2calc ==1.8.2
Requires-Dist: bw2data ==3.6.6
Requires-Dist: bw2io ==0.8.12
Requires-Dist: bw2parameters >=0.6.5
Requires-Dist: docopt
Requires-Dist: eight
Requires-Dist: flask
Requires-Dist: future
Requires-Dist: lxml
Requires-Dist: numpy
Requires-Dist: peewee >=3.0
Requires-Dist: psutil
Requires-Dist: pyprind
Requires-Dist: requests
Requires-Dist: scipy
Requires-Dist: stats-arrays >=0.6.5
Requires-Dist: unicodecsv
Requires-Dist: voluptuous
Requires-Dist: whoosh
Requires-Dist: xlrd
Requires-Dist: xlsxwriter
